{"title":"Jacob的博客","description":"雅克布, 85后双鱼座普通男青年！喜欢敲代码的感觉，相信变成是一门艺术，自诩为游弋在代码里的人生","language":"","link":"//jacob.cool","pubDate":"Sat, 25 Mar 2017 12:00:46 GMT","lastBuildDate":"Sun, 23 Apr 2017 09:07:19 GMT","generator":"hexo-generator-json-feed","webMaster":"Jacob","items":[{"title":"开通个人博客 - Hexo","link":"//jacob.cool/2017/03/25/open-my-own-blog-with-hexo/","description":"如果你也想搭建自己的个人博客，请参考《HEXO搭建个人博客》 推荐一个比较好用的图床 Z4A图床 想捣鼓自己的博客有一段时间了，简书是一个不错的写作平台，在这里我读到了很多优秀的文章，学习到了很多新鲜的知识，无论是技术方面还是生活感悟、工作技巧、奇闻异事，我很喜欢在这里看文章的那种感觉，但是我觉得作为一个Developer，有一个自己的博客，写下自己的经验，写下自己的生活必不可少，积累是一个人一生最宝贵的财富。 我看过很多开发者写博客的平台，博客园，CSDN，也尝试过多种搭建博客的方式，最后我被GithubPages + Hexo吸引了，简洁大方，高逼格。 经过今天不懈的努力，域名也成功解析了，http://jacob.cool 正式生效了。","pubDate":"Sat, 25 Mar 2017 12:00:46 GMT","guid":"//jacob.cool/2017/03/25/open-my-own-blog-with-hexo/","category":"博客,hexo - villa"}]}